qcloud_vod_migrate/__init__.py
qcloud_vod_migrate/cmd.py
qcloud_vod_migrate/config.py
qcloud_vod_migrate/execute.py
qcloud_vod_migrate/manager.py
qcloud_vod_migrate/upload.py
qcloud_vod_migrate/util.py
vodmigrate-1.0.12.data/data/README.md
vodmigrate-1.0.12.dist-info/LICENSE
vodmigrate-1.0.12.dist-info/METADATA
vodmigrate-1.0.12.dist-info/WHEEL
vodmigrate-1.0.12.dist-info/entry_points.txt
vodmigrate-1.0.12.dist-info/top_level.txt
vodmigrate-1.0.12.dist-info/RECORD
