Metadata-Version: 2.1
Name: vodmigrate
Version: 1.0.12
Summary: vod migrate tool
Home-page: https://www.qcloud.com/
Author: vod
Author-email: 286242216@qq.com
License: MIT
Platform: UNKNOWN
Requires-Dist: toml
Requires-Dist: sqlalchemy
Requires-Dist: munch
Requires-Dist: six
Requires-Dist: python-dateutil
Requires-Dist: vod-python-sdk
Requires-Dist: oss2
Requires-Dist: boto3
Requires-Dist: qiniu
